saltpeter/__init__.py
saltpeter/machines_endpoint.py
saltpeter/main.py
saltpeter/timeline.py
saltpeter/ui_endpoint.py
saltpeter/version.py
saltpeter/wrapper.py
saltpeter-0.9.30.dist-info/METADATA
saltpeter-0.9.30.dist-info/WHEEL
saltpeter-0.9.30.dist-info/entry_points.txt
saltpeter-0.9.30.dist-info/top_level.txt
saltpeter-0.9.30.dist-info/RECORD
