Metadata-Version: 2.4
Name: saltpeter
Version: 0.9.30
Summary: Distributed cron based on salt
Home-page: http://github.com/syscollective/saltpeter
Author: Marin Vintila
Author-email: marin.vintila@syscollective.com
License: MIT
Requires-Dist: websocket
Requires-Dist: crontab
Requires-Dist: pyyaml
Requires-Dist: elasticsearch
Requires-Dist: opensearch-py
Dynamic: author
Dynamic: author-email
Dynamic: description
Dynamic: home-page
Dynamic: license
Dynamic: requires-dist
Dynamic: summary
